<?xml version="1.0" encoding="UTF-8"?>
<dispatchDataResponse
    xmlns="http://www.broservices.nl/xsd/dsgmn/1.0"
    xmlns:brocom="http://www.broservices.nl/xsd/brocommon/3.0"
    xmlns:gml="http://www.opengis.net/gml/3.2"
    xmlns:xlink="http://www.w3.org/1999/xlink"
    xmlns:xsi="http://www.w3.org/2001/XMLSchema-instance"
    xsi:schemaLocation="http://www.broservices.nl/xsd/dsgmn/1.0 ../../XSD/dsgmn-messages.xsd"
    >
  <!-- Disclaimer: dit voorbeeldbericht valideert tegen de XSD van de uitgifteservice.
       Het is niet gevalideert door de uitgifteservice en is vaktechnisch/inhoudelijk niet voorbeeldig.
  -->
  <brocom:responseType>rejection</brocom:responseType>
  <brocom:requestReference>uitgifte-38</brocom:requestReference>
  <!-- optional. Alleen aanwezig als responseType = rejection. -->
  <brocom:rejectionTime>2020-12-31T13:16:17+02:00</brocom:rejectionTime>
  <!-- optional. Alleen aanwezig als responseType = dispatch.
  <brocom:dispatchTime>2020-08-15T13:16:17+02:00</brocom:dispatchTime>
  -->
  <!-- optional. Alleen aanwezig als responseType = rejection. -->
  <brocom:rejectionReason>Dit registratieobject bestaat niet.</brocom:rejectionReason>
  <!-- 0 or more repetitions: Alleen aanwezig als responseType = rejection. -->
  <brocom:criterionError>
    <brocom:sequenceNumber>1</brocom:sequenceNumber>
    <brocom:specification>...</brocom:specification>
  </brocom:criterionError>
  <!-- optional. Alleen aanwezig als responseType = dispatch.
  <dispatchDocument>
    ...
  </dispatchDocument>
  -->
</dispatchDataResponse>
